{"config": {"view": {"continuousWidth": 300, "continuousHeight": 300, "strokeWidth": 0}, "axisY": {"grid": true, "gridOpacity": 0.25}, "legend": {"orient": "right", "padding": 8}}, "layer": [{"mark": {"type": "bar", "stroke": "white", "strokeWidth": 1}, "encoding": {"color": {"field": "control", "legend": {"title": null}, "scale": {"domain": ["In control", "Out of Control"], "range": ["#2563eb", "#6b7280"]}, "type": "nominal"}, "x": {"axis": {"labelAngle": -35, "labelLimit": 280, "title": null}, "field": "label", "sort": ["Poor diet, score 1\u20132 / 5", "Occupational exposure", "High air pollution, top 25% percentile", "Alcohol,   15+ Drinks per week", "Exercise, <2 Hours per week", "Secondhand smoke", "Age 60+", "Family history", "Over 20 cigs per day", "COPD diagnosis", "High pack-years, top 25% percentile"], "type": "nominal"}, "y": {"field": "difference", "scale": {"domain": [0, 68.00230201831889]}, "title": "Difference in cancer prevalence", "type": "quantitative"}}, "title": "Change in lung cancer rate"}, {"mark": {"type": "text", "color": "#262626", "dy": -6, "size": 9}, "encoding": {"text": {"field": "difference", "format": ".1f", "type": "quantitative"}, "x": {"field": "label", "sort": ["Poor diet, score 1\u20132 / 5", "Occupational exposure", "High air pollution, top 25% percentile", "Alcohol,   15+ Drinks per week", "Exercise, <2 Hours per week", "Secondhand smoke", "Age 60+", "Family history", "Over 20 cigs per day", "COPD diagnosis", "High pack-years, top 25% percentile"], "type": "nominal"}, "y": {"field": "difference", "type": "quantitative"}}, "title": "Change in lung cancer rate"}, {"mark": {"type": "rule", "color": "#666666", "strokeWidth": 0.8}, "encoding": {"y": {"datum": 0}}}], "data": {"name": "data-2db3ed74e049d0c87172c19b1ed93330"}, "height": 420, "width": 900, "$schema": "https://vega.github.io/schema/vega-lite/v6.1.0.json", "datasets": {"data-2db3ed74e049d0c87172c19b1ed93330": [{"label": "Poor diet, score 1\u20132 / 5", "negative": 53.57142857142857, "positive": 55.86145648312611, "modifiable": true, "difference": 2.2900279116975426, "control": "In control"}, {"label": "Occupational exposure", "negative": 53.360370799536504, "positive": 58.941605839416056, "modifiable": true, "difference": 5.581235039879552, "control": "In control"}, {"label": "High air pollution, top 25% percentile", "negative": 53.13609467455621, "positive": 59.24657534246576, "modifiable": false, "difference": 6.110480667909549, "control": "Out of Control"}, {"label": "Alcohol,   15+ Drinks per week", "negative": 54.4540886249429, "positive": 61.1764705882353, "modifiable": true, "difference": 6.722381963292399, "control": "In control"}, {"label": "Exercise, <2 Hours per week", "negative": 52.338811630847026, "positive": 60.115606936416185, "modifiable": true, "difference": 7.776795305569159, "control": "In control"}, {"label": "Secondhand smoke", "negative": 51.797603195739015, "positive": 60.362694300518136, "modifiable": true, "difference": 8.565091104779121, "control": "In control"}, {"label": "Age 60+", "negative": 51.23911587407903, "positive": 61.33162612035852, "modifiable": false, "difference": 10.092510246279488, "control": "Out of Control"}, {"label": "Family history", "negative": 52.348993288590606, "positive": 63.37448559670782, "modifiable": false, "difference": 11.025492308117215, "control": "Out of Control"}, {"label": "Over 20 cigs per day", "negative": 46.211251435132034, "positive": 82.5187969924812, "modifiable": true, "difference": 36.307545557349165, "control": "In control"}, {"label": "COPD diagnosis", "negative": 37.77928232904536, "positive": 86.07277289836888, "modifiable": false, "difference": 48.293490569323524, "control": "Out of Control"}, {"label": "High pack-years, top 25% percentile", "negative": 39.112426035502956, "positive": 99.82876712328768, "modifiable": true, "difference": 60.71634108778472, "control": "In control"}]}}